heu.so
sf_heu-0.6.0.dev20250514.dist-info/licenses/LICENSE
sf_heu-0.6.0.dev20250514.dist-info/METADATA
sf_heu-0.6.0.dev20250514.dist-info/WHEEL
sf_heu-0.6.0.dev20250514.dist-info/top_level.txt
sf_heu-0.6.0.dev20250514.dist-info/RECORD
