Metadata-Version: 2.4
Name: sf_heu
Version: 0.6.0.dev20250514
Summary: Homomorphic Encryption processing Unit (HEU) is a subproject of Secretflow that implements high-performance homomorphic encryption algorithms.
Home-page: https://github.com/secretflow/heu
Author: SecretFlow Team
Author-email: secretflow-contact@service.alipay.com
License: Apache 2.0
Classifier: Programming Language :: Python :: 3.9
Classifier: Programming Language :: Python :: 3.10
Classifier: Programming Language :: Python :: 3.11
License-File: LICENSE
Requires-Dist: numpy>=1.22.0
Dynamic: author
Dynamic: author-email
Dynamic: classifier
Dynamic: description
Dynamic: description-content-type
Dynamic: home-page
Dynamic: license
Dynamic: license-file
Dynamic: requires-dist
Dynamic: summary
